core/defs.vh
`ifndef DEFS_VH
`define DEFS_VH

// Utility definitions
`define W(width) [(width)-1:0]

// System Constants
`define DLEN              64 // data width
`define ILEN              32 // instruction width
`define RLEN              5  // register index width
`define OLEN              7  // opcode width
`define F3LEN             3  // funct3 width
`define F7LEN             7  // funct7 width

// slices from instructions
`define OSLICE            [6:0]   // opcode
`define F3SLICE           [14:12] // funct3
`define F7SLICE           [31:25] // funct7

// OPcodes wrt instruction format
// to be used in case block ONLY
`define OP_R              7'b0110011
// normal imm instr, loads, jalr, ecall
`define OP_I              7'b0010011, 7'b0000011, 7'b1100111, 7'b1110011
`define OP_S              7'b0100011
`define OP_B              7'b1100011
`define OP_U              7'b0110111, 7'b0010111
`define OP_J              7'b1101111

// Bunch opcodes (BOPcodes)
// bunch is defined as {opcode, funct3, funct7}
// 'z' will be used in casez for control sigs
`define BOP_ADD           17'b0110011_000_0000000
`define BOP_ADDI          17'b0010011_000_zzzzzzz
`define BOP_LB            17'b0000011_000_zzzzzzz
`define BOP_LH            17'b0000011_001_zzzzzzz
`define BOP_LW            17'b0000011_010_zzzzzzz
`define BOP_LD            17'b0000011_011_zzzzzzz
`define BOP_LBU           17'b0000011_100_zzzzzzz
`define BOP_LHU           17'b0000011_101_zzzzzzz
`define BOP_SB            17'b0100011_000_zzzzzzz
`define BOP_SH            17'b0100011_001_zzzzzzz
`define BOP_SW            17'b0100011_010_zzzzzzz
`define BOP_SD            17'b0100011_011_zzzzzzz
`define BOP_SUB           17'b0110011_000_0100000
`define BOP_SLT           17'b0110011_010_0000000
`define BOP_SLTU          17'b0110011_011_0000000
`define BOP_SLL           17'b0110011_001_0000000
`define BOP_SRL           17'b0110011_101_0000000
`define BOP_SRA           17'b0110011_101_0100000
`define BOP_XOR           17'b0110011_100_0000000
`define BOP_OR            17'b0110011_110_0000000
`define BOP_AND           17'b0110011_111_0000000
`define BOP_SLTI          17'b0010011_010_zzzzzzz
`define BOP_SLTIU         17'b0010011_011_zzzzzzz
`define BOP_SLLI          17'b0010011_001_zzzzzzz
`define BOP_SRLI          17'b0010011_101_zzzzzzz 
`define BOP_SRAI          17'b0010011_101_zzzzzzz // same as SRLI except upper bits of imm
`define BOP_XORI          17'b0010011_100_zzzzzzz
`define BOP_ORI           17'b0010011_110_zzzzzzz
`define BOP_ANDI          17'b0010011_111_zzzzzzz

// ALU OPCodes (custom defined)
`define ALU_OP_W          4

`define ALU_OP_ADD        4'h0
`define ALU_OP_SUB        4'h1
`define ALU_OP_XOR        4'h2
`define ALU_OP_OR         4'h3
`define ALU_OP_AND        4'h4
`define ALU_OP_SLL        4'h5
`define ALU_OP_SRL        4'h6
`define ALU_OP_SRA        4'h7
`define ALU_OP_SLT        4'h8
`define ALU_OP_SLTU       4'h9

`endif

core/immgen.v
`include "defs.vh"

// ref: https://www.cs.sfu.ca/~ashriram/Courses/CS295/assets/notebooks/RISCV/RISCV_CARD.pdf

/* verilator lint_off WIDTHEXPAND */
module immgen (
  input wire `W(`ILEN) instr,
  output reg `W(`DLEN) imm
);
  wire `W(`OLEN)  opcode = instr`OSLICE;

  // WARNING! This code is standalone and isnt dependent on macros
  // defined in defs.vh, change this when defs.vh is edited
  always @(*) begin
    case(opcode)
      `OP_R:   imm = 0;
      `OP_I:   imm = $signed(instr[31:20]);
      `OP_S:   imm = $signed({instr[31:25], instr[11:7]});
      `OP_B:   imm = $signed({instr[31], instr[7], instr[30:25], instr[11:8], 1'b0});
      `OP_U:   imm = $signed({instr[31:12], 12'b0});
      `OP_J:   imm = $signed({instr[31], instr[19:12], instr[20], instr[30:21], 1'b0});
      default: imm = 0; 
    endcase
  end
endmodule
/* verilator lint_on WIDTHEXPAND */

immgen_trace.vcd
$version Generated by VerilatedVcd $end
$timescale 1ps $end
 $scope module TOP $end
  $var wire 32 " instr [31:0] $end
  $var wire 64 # imm [63:0] $end
  $scope module immgen $end
   $var wire 32 " instr [31:0] $end
   $var wire 64 # imm [63:0] $end
   $var wire 7 % opcode [6:0] $end
  $upscope $end
 $upscope $end
$enddefinitions $end


#0
b00000000001100010000000010110011 "
b0000000000000000000000000000000000000000000000000000000000000000 #
b0110011 %
#1
b01111111111100000000000010010011 "
b0000000000000000000000000000000000000000000000000000011111111111 #
b0010011 %
#2
b10000000000000000000000010010011 "
b1111111111111111111111111111111111111111111111111111100000000000 #
#3
b01111110001000001010111110100011 "
b0000000000000000000000000000000000000000000000000000011111111111 #
b0100011 %
#4
b10000000001000001010000000100011 "
b1111111111111111111111111111111111111111111111111111100000000000 #
#5
b01111110001000001000111111100011 "
b0000000000000000000000000000000000000000000000000000111111111110 #
b1100011 %
#6
b10000000001000001000000001100011 "
b1111111111111111111111111111111111111111111111111111000000000000 #
#7
b00010010001101000101000010110111 "
b0000000000000000000000000000000000010010001101000101000000000000 #
b0110111 %
#8
b10000111011001010100000010110111 "
b1111111111111111111111111111111110000111011001010100000000000000 #
#9
b01111111111111111111000011101111 "
b0000000000000000000000000000000000000000000011111111111111111110 #
b1101111 %
#10
b10000000000000000000000011101111 "
b1111111111111111111111111111111111111111111100000000000000000000 #
#11
b00001010101111101010100001101111 "
b0000000000000000000000000000000000000000000011101010100010101010 #
